ailist/AIList_core.cpython-312-darwin.so
ailist/AIList_core.pxd
ailist/AIList_core.pyx
ailist/IntervalArray_core.py
ailist/Interval_core.cpython-312-darwin.so
ailist/Interval_core.pxd
ailist/Interval_core.pyx
ailist/LabeledIntervalArray_core.cpython-312-darwin.so
ailist/LabeledIntervalArray_core.pxd
ailist/LabeledIntervalArray_core.pyx
ailist/__init__.py
ailist/array_query_core.cpython-312-darwin.so
ailist/array_query_core.pxd
ailist/array_query_core.pyx
ailist/src/ailist/ailist_add.c
ailist/src/ailist/ailist_closest.c
ailist/src/ailist/ailist_construct.c
ailist/src/ailist/ailist_coverage.c
ailist/src/ailist/ailist_extract.c
ailist/src/ailist/ailist_filter.c
ailist/src/ailist/ailist_get_id.c
ailist/src/ailist/ailist_iter.c
ailist/src/ailist/ailist_merge.c
ailist/src/ailist/ailist_nhits.c
ailist/src/ailist/ailist_ops.c
ailist/src/ailist/ailist_query.c
ailist/src/ailist/ailist_simulate.c
ailist/src/ailist/ailist_wps.c
ailist/src/ailist/augmented_interval_list.c
ailist/src/ailist/augmented_interval_list.h
ailist/src/ailist/interval.c
ailist/src/ailist/interval.h
ailist/src/ailist/overlap_index.c
ailist/src/array_query/array_query_utilities.c
ailist/src/array_query/array_query_utilities.h
ailist/src/labeled_aiarray/khash.h
ailist/src/labeled_aiarray/kvec.h
ailist/src/labeled_aiarray/labeled_aiarray_add.c
ailist/src/labeled_aiarray/labeled_aiarray_construct.c
ailist/src/labeled_aiarray/labeled_aiarray_coverage.c
ailist/src/labeled_aiarray/labeled_aiarray_extract.c
ailist/src/labeled_aiarray/labeled_aiarray_filter.c
ailist/src/labeled_aiarray/labeled_aiarray_get.c
ailist/src/labeled_aiarray/labeled_aiarray_index.c
ailist/src/labeled_aiarray/labeled_aiarray_iter.c
ailist/src/labeled_aiarray/labeled_aiarray_match.c
ailist/src/labeled_aiarray/labeled_aiarray_merge.c
ailist/src/labeled_aiarray/labeled_aiarray_nhits.c
ailist/src/labeled_aiarray/labeled_aiarray_ops.c
ailist/src/labeled_aiarray/labeled_aiarray_percent.c
ailist/src/labeled_aiarray/labeled_aiarray_query_array.c
ailist-2.1.7.dist-info/LICENSE.md
ailist-2.1.7.dist-info/METADATA
ailist-2.1.7.dist-info/WHEEL
ailist-2.1.7.dist-info/RECORD
